utsk/__init__.py
utsk/_schemas.py
utsk/_unthread.py
utsk/_utils.py
utsk-0.0.12.dist-info/METADATA
utsk-0.0.12.dist-info/WHEEL
utsk-0.0.12.dist-info/RECORD
