Metadata-Version: 2.1
Name: utsk
Version: 0.0.12
Summary: Utsk!
License: MIT
Author: William Fu-Hinthorn
Author-email: 13333726+hinthornw@users.noreply.github.com
Requires-Python: >=3.10,<4.0
Classifier: License :: OSI Approved :: MIT License
Classifier: Programming Language :: Python :: 3
Classifier: Programming Language :: Python :: 3.10
Classifier: Programming Language :: Python :: 3.11
Classifier: Programming Language :: Python :: 3.12
Requires-Dist: httpx (>=0.27.0,<0.28.0)
